{
  "add_dessert": {
    "precision": 1.0,
    "recall": 1.0,
    "f1-score": 1.0,
    "support": 84,
    "confused_with": {}
  },
  "decline_offer": {
    "precision": 1.0,
    "recall": 1.0,
    "f1-score": 1.0,
    "support": 47,
    "confused_with": {}
  },
  "provide_address": {
    "precision": 1.0,
    "recall": 1.0,
    "f1-score": 1.0,
    "support": 255,
    "confused_with": {}
  },
  "place_order": {
    "precision": 1.0,
    "recall": 1.0,
    "f1-score": 1.0,
    "support": 57,
    "confused_with": {}
  },
  "confirm_order": {
    "precision": 1.0,
    "recall": 1.0,
    "f1-score": 1.0,
    "support": 37,
    "confused_with": {}
  },
  "ask_delivery_time": {
    "precision": 1.0,
    "recall": 1.0,
    "f1-score": 1.0,
    "support": 32,
    "confused_with": {}
  },
  "show_menu": {
    "precision": 1.0,
    "recall": 1.0,
    "f1-score": 1.0,
    "support": 54,
    "confused_with": {}
  },
  "order_burger": {
    "precision": 1.0,
    "recall": 1.0,
    "f1-score": 1.0,
    "support": 86,
    "confused_with": {}
  },
  "order_food": {
    "precision": 1.0,
    "recall": 1.0,
    "f1-score": 1.0,
    "support": 197,
    "confused_with": {}
  },
  "add_drink": {
    "precision": 1.0,
    "recall": 1.0,
    "f1-score": 1.0,
    "support": 42,
    "confused_with": {}
  },
  "thankyou": {
    "precision": 1.0,
    "recall": 0.9,
    "f1-score": 0.9473684210526316,
    "support": 10,
    "confused_with": {
      "goodbye": 1
    }
  },
  "cancel_order": {
    "precision": 1.0,
    "recall": 1.0,
    "f1-score": 1.0,
    "support": 156,
    "confused_with": {}
  },
  "goodbye": {
    "precision": 0.9807692307692307,
    "recall": 1.0,
    "f1-score": 0.9902912621359222,
    "support": 51,
    "confused_with": {}
  },
  "select_cuisine": {
    "precision": 1.0,
    "recall": 1.0,
    "f1-score": 1.0,
    "support": 66,
    "confused_with": {}
  },
  "greet": {
    "precision": 1.0,
    "recall": 1.0,
    "f1-score": 1.0,
    "support": 101,
    "confused_with": {}
  },
  "accuracy": 0.9992156862745099,
  "macro avg": {
    "precision": 0.9987179487179486,
    "recall": 0.9933333333333334,
    "f1-score": 0.9958439788792369,
    "support": 1275
  },
  "weighted avg": {
    "precision": 0.9992307692307691,
    "recall": 0.9992156862745099,
    "f1-score": 0.9991988537878104,
    "support": 1275
  },
  "micro avg": {
    "precision": 0.9992156862745099,
    "recall": 0.9992156862745099,
    "f1-score": 0.9992156862745099,
    "support": 1275
  }
}